README.rst
setup.py
ascension_kit/__init__.py
ascension_kit/ascension_kit.py
ascension_kit/format.py
ascension_kit/nao.py
ascension_kit/utils.py
ascension_kit.egg-info/PKG-INFO
ascension_kit.egg-info/SOURCES.txt
ascension_kit.egg-info/dependency_links.txt
ascension_kit.egg-info/not-zip-safe
ascension_kit.egg-info/requires.txt
ascension_kit.egg-info/top_level.txt
bin/ascension-kit