Metadata-Version: 1.1
Name: ascension-kit
Version: 0.0.14
Summary: A utility to report ascension information from NAO.
Home-page: http://packages.python.org/ascension_kit
Author: Greg Moselle
Author-email: zomgreg+ascensionkit@gmail.com
License: BSD
Keywords: python nethack utility
Platform: UNKNOWN
Classifier: Development Status :: 3 - Alpha
Classifier: Topic :: Utilities
Classifier: License :: OSI Approved :: BSD License
